micro_nats/__init__.py
micro_nats/client.py
micro_nats/error.py
micro_nats/model.py
micro_nats/io/__init__.py
micro_nats/io/manager.py
micro_nats/jetstream/__init__.py
micro_nats/jetstream/client.py
micro_nats/jetstream/error.py
micro_nats/jetstream/io/__init__.py
micro_nats/jetstream/io/inbox.py
micro_nats/jetstream/io/manager/__init__.py
micro_nats/jetstream/io/manager/consumer.py
micro_nats/jetstream/io/manager/message.py
micro_nats/jetstream/io/manager/stream.py
micro_nats/jetstream/protocol/__init__.py
micro_nats/jetstream/protocol/ack.py
micro_nats/jetstream/protocol/consumer.py
micro_nats/jetstream/protocol/server.py
micro_nats/jetstream/protocol/stream.py
micro_nats/protocol/__init__.py
micro_nats/protocol/cmd/__init__.py
micro_nats/protocol/cmd/client.py
micro_nats/protocol/cmd/server.py
micro_nats/util/__init__.py
micro_nats/util/asynchronous.py
micro_nats/util/headers.py
micro_nats/util/uri.py
micro_nats-1.0.2.dist-info/METADATA
micro_nats-1.0.2.dist-info/WHEEL
micro_nats-1.0.2.dist-info/top_level.txt
micro_nats-1.0.2.dist-info/RECORD
