Metadata-Version: 2.1
Name: micro-nats
Version: 1.0.2
Summary: A MicroPython NATS client
Home-page: https://github.com/jordonsc/inu-py
Author: Jordon Scott
Author-email: jordonsc@gmail.com
License: MIT
Platform: UNKNOWN
